odoo9_addon_datetime_formatter-9.0.1.0.0-py2.7-nspkg.pth
odoo_addons/datetime_formatter/models.py
odoo_addons/datetime_formatter/__openerp__.py
odoo_addons/datetime_formatter/__init__.py
odoo_addons/datetime_formatter/exceptions.py
odoo_addons/datetime_formatter/README.rst
odoo_addons/datetime_formatter/i18n/it.po
odoo_addons/datetime_formatter/i18n/es.po
odoo_addons/datetime_formatter/i18n/tr.po
odoo_addons/datetime_formatter/i18n/sl.po
odoo_addons/datetime_formatter/i18n/de.po
odoo_addons/datetime_formatter/i18n/fr.po
odoo_addons/datetime_formatter/tests/test_formatter.py
odoo_addons/datetime_formatter/tests/test_best_matcher.py
odoo_addons/datetime_formatter/tests/__init__.py
odoo_addons/datetime_formatter/static/description/icon.png
odoo9_addon_datetime_formatter-9.0.1.0.0.dist-info/top_level.txt
odoo9_addon_datetime_formatter-9.0.1.0.0.dist-info/WHEEL
odoo9_addon_datetime_formatter-9.0.1.0.0.dist-info/RECORD
odoo9_addon_datetime_formatter-9.0.1.0.0.dist-info/metadata.json
odoo9_addon_datetime_formatter-9.0.1.0.0.dist-info/DESCRIPTION.rst
odoo9_addon_datetime_formatter-9.0.1.0.0.dist-info/METADATA
odoo9_addon_datetime_formatter-9.0.1.0.0.dist-info/namespace_packages.txt
